{"ER_YES": "\"SI\"", "ER_CANT_CREATE_FILE": "\"Impossibile creare il file '%-.200s' (errno: %M)\"", "ER_CANT_CREATE_TABLE": "\"Impossibile creare la tabella %`s.%`s (errno: %M)\"", "ER_CANT_CREATE_DB": "\"Impossibile creare il database '%-.192s' (errno: %M)\"", "ER_DB_CREATE_EXISTS": "\"Impossibile creare il database '%-.192s'; il database esiste\"", "ER_DB_DROP_EXISTS": "\"Impossibile cancellare '%-.192s'; il database non esiste\"", "ER_DB_DROP_DELETE": "\"Errore durante la cancellazione del database (impossibile cancellare '%-.192s', errno: %M)\"", "ER_DB_DROP_RMDIR": "\"Errore durante la cancellazione del database (impossibile rmdir '%-.192s', errno: %M)\"", "ER_CANT_DELETE_FILE": "\"Errore durante la cancellazione di '%-.192s' (errno: %M)\"", "ER_CANT_FIND_SYSTEM_REC": "\"Impossibile leggere il record dalla tabella di sistema\"", "ER_CANT_GET_STAT": "\"Impossibile leggere lo stato di '%-.200s' (errno: %M)\"", "ER_CANT_GET_WD": "\"Impossibile leggere la directory di lavoro (errno: %M)\"", "ER_CANT_LOCK": "\"Impossibile il locking il file (errno: %M)\"", "ER_CANT_OPEN_FILE": "\"Impossibile aprire il file: '%-.200s' (errno: %M)\"", "ER_FILE_NOT_FOUND": "\"Impossibile trovare il file: '%-.200s' (errno: %M)\"", "ER_CANT_READ_DIR": "\"Impossibile leggere la directory di '%-.192s' (errno: %M)\"", "ER_CANT_SET_WD": "\"Impossibile cambiare la directory in '%-.192s' (errno: %M)\"", "ER_CHECKREAD": "\"Il record e` cambiato dall'ultima lettura della tabella '%-.192s'\"", "ER_DISK_FULL": "\"Disco pieno (%s). In attesa che qualcuno liberi un po' di spazio... (errno: %M)\"", "ER_DUP_KEY 23000": "\"Scrittura impossibile: chiave duplicata nella tabella '%-.192s'\"", "ER_ERROR_ON_CLOSE": "\"Errore durante la chiusura di '%-.192s' (errno: %M)\"", "ER_ERROR_ON_READ": "\"Errore durante la lettura del file '%-.200s' (errno: %M)\"", "ER_ERROR_ON_RENAME": "\"Errore durante la rinominazione da '%-.210s' a '%-.210s' (errno: %M)\"", "ER_ERROR_ON_WRITE": "\"Errore durante la scrittura del file '%-.200s' (errno: %M)\"", "ER_FILE_USED": "\"'%-.192s' e` soggetto a lock contro i cambiamenti\"", "ER_FILSORT_ABORT": "\"Operazione di ordinamento abbandonata\"", "ER_FORM_NOT_FOUND": "\"La view '%-.192s' non esiste per '%-.192s'\"", "ER_GET_ERRNO": "\"Rilevato l'errore %M dal gestore delle tabelle %s\"", "ER_KEY_NOT_FOUND": "\"Impossibile trovare il record in '%-.192s'\"", "ER_NOT_FORM_FILE": "\"Informazione errata nel file: '%-.200s'\"", "ER_NOT_KEYFILE": "\"File chiave errato per la tabella : '%-.200s'; prova a riparalo\"", "ER_OLD_KEYFILE": "\"File chiave vecchio per la tabella '%-.192s'; riparalo!\"", "ER_OPEN_AS_READONLY": "\"'%-.192s' e` di sola lettura\"", "ER_OUTOFMEMORY HY001 S1001": "\"Memoria esaurita. Fai ripartire il demone e riprova (richiesti %d bytes)\"", "ER_OUT_OF_SORTMEMORY HY001 S1001": "\"Memoria per gli ordinamenti esaurita. Incrementare il 'sort_buffer' al demone\"", "ER_UNEXPECTED_EOF": "\"Fine del file inaspettata durante la lettura del file '%-.192s' (errno: %M)\"", "ER_CON_COUNT_ERROR 08004": "\"Troppe connessioni\"", "ER_OUT_OF_RESOURCES": "\"Fine dello spazio/memoria per i thread\"", "ER_BAD_HOST_ERROR 08S01": "\"Impossibile risalire al nome dell'host dall'indirizzo (risoluzione inversa)\"", "ER_HANDSHAKE_ERROR 08S01": "\"Negoziazione impossibile\"", "ER_DBACCESS_DENIED_ERROR 42000": "\"Accesso non consentito per l'utente: '%s'@'%s' al database '%-.192s'\"", "ER_ACCESS_DENIED_ERROR 28000": "\"Accesso non consentito per l'utente: '%s'@'%s' (Password: %s)\"", "ER_NO_DB_ERROR 3D000": "\"Nessun database selezionato\"", "ER_UNKNOWN_COM_ERROR 08S01": "\"Comando sconosciuto\"", "ER_BAD_NULL_ERROR 23000": "\"La colonna '%-.192s' non puo` essere nulla\"", "ER_BAD_DB_ERROR 42000": "\"Database '%-.192s' sconosciuto\"", "ER_TABLE_EXISTS_ERROR 42S01": "\"La tabella '%-.192s' esiste gia`\"", "ER_BAD_TABLE_ERROR 42S02": "\"Tabella '%-.100T' sconosciuta\"", "ER_NON_UNIQ_ERROR 23000": "\"Colonna: '%-.192s' di %-.192s e` ambigua\"", "ER_SERVER_SHUTDOWN 08S01": "\"Shutdown del server in corso\"", "ER_BAD_FIELD_ERROR 42S22 S0022": "\"Colonna sconosciuta '%-.192s' in '%-.192s'\"", "ER_WRONG_FIELD_WITH_GROUP 42000 S1009": "\"Usato '%-.192s' che non e` nel GROUP BY\"", "ER_WRONG_GROUP_FIELD 42000 S1009": "\"Impossibile raggruppare per '%-.192s'\"", "ER_WRONG_SUM_SELECT 42000 S1009": "\"Il comando ha una funzione SUM e una colonna non specificata nella GROUP BY\"", "ER_WRONG_VALUE_COUNT 21S01": "\"Il numero delle colonne non e` uguale al numero dei valori\"", "ER_TOO_LONG_IDENT 42000 S1009": "\"Il nome dell'identificatore '%-.100T' e` troppo lungo\"", "ER_DUP_FIELDNAME 42S21 S1009": "\"Nome colonna duplicato '%-.192s'\"", "ER_DUP_KEYNAME 42000 S1009": "\"Nome chiave duplicato '%-.192s'\"", "ER_DUP_ENTRY 23000 S1009": "\"Valore duplicato '%-.192T' per la chiave %d\"", "ER_WRONG_FIELD_SPEC 42000 S1009": "\"Specifica errata per la colonna '%-.192s'\"", "ER_PARSE_ERROR 42000 s1009": "\"%s vicino a '%-.80T' linea %d\"", "ER_EMPTY_QUERY 42000": "\"La query e` vuota\"", "ER_NONUNIQ_TABLE 42000 S1009": "\"Tabella/alias non unico: '%-.192s'\"", "ER_INVALID_DEFAULT 42000 S1009": "\"Valore di default non valido per '%-.192s'\"", "ER_MULTIPLE_PRI_KEY 42000 S1009": "\"Definite piu` chiave primarie\"", "ER_TOO_MANY_KEYS 42000 S1009": "\"Troppe chiavi. Sono ammesse max %d chiavi\"", "ER_TOO_MANY_KEY_PARTS 42000 S1009": "\"Troppe parti di chiave specificate. Sono ammesse max %d parti\"", "ER_TOO_LONG_KEY 42000 S1009": "\"La chiave specificata e` troppo lunga. La max lunghezza della chiave e` %d\"", "ER_KEY_COLUMN_DOES_NOT_EXIST 42000 S1009": "\"La colonna chiave '%-.192s' non esiste nella tabella\"", "ER_TOO_BIG_FIELDLENGTH 42000 S1009": "\"La colonna '%-.192s' e` troppo grande (max=%lu). Utilizza un BLOB\"", "ER_WRONG_AUTO_KEY 42000 S1009": "\"Puo` esserci solo un campo AUTO e deve essere definito come chiave\"", "ER_NORMAL_SHUTDOWN": "\"%s (%s): Shutdown normale\"", "ER_GOT_SIGNAL": "\"%s: Ricevuto segnale %d. Interruzione!\\n\"", "ER_SHUTDOWN_COMPLETE": "\"%s: Shutdown completato\\n\"", "ER_FORCING_CLOSE 08S01": "\"%s: Forzata la chiusura del thread %ld utente: '%-.48s'\\n\"", "ER_IPSOCK_ERROR 08S01": "\"Impossibile creare il socket IP\"", "ER_NO_SUCH_INDEX 42S12 S1009": "\"La tabella '%-.192s' non ha nessun indice come quello specificatato dalla CREATE INDEX. Ricrea la tabella\"", "ER_WRONG_FIELD_TERMINATORS 42000 S1009": "\"L'argomento 'Field separator' non e` quello atteso. Controlla il manuale\"", "ER_BLOBS_AND_NO_TERMINATED 42000 S1009": "\"Non possono essere usate righe a lunghezza fissa con i BLOB. Usa 'FIELDS TERMINATED BY'\"", "ER_TEXTFILE_NOT_READABLE": "\"Il file '%-.128s' deve essere nella directory del database e deve essere leggibile da tutti\"", "ER_FILE_EXISTS_ERROR": "\"Il file '%-.200s' esiste gia`\"", "ER_LOAD_INFO": "\"Records: %ld  Cancellati: %ld  Saltati: %ld  Avvertimenti: %ld\"", "ER_ALTER_INFO": "\"Records: %ld  Duplicati: %ld\"", "ER_WRONG_SUB_KEY": "\"Sotto-parte della chiave errata. La parte di chiave utilizzata non e` una stringa o la lunghezza e` maggiore della parte di chiave\"", "ER_CANT_REMOVE_ALL_FIELDS 42000": "\"Non si possono cancellare tutti i campi con una ALTER TABLE. Utilizzare DROP TABLE\"", "ER_CANT_DROP_FIELD_OR_KEY 42000": "\"Impossibile cancellare (DROP %s) %`-.192s. Controllare che il campo chiave esista\"", "ER_INSERT_INFO": "\"Records: %ld  Duplicati: %ld  Avvertimenti: %ld\"", "ER_NO_SUCH_THREAD": "\"Thread id: %lu sconosciuto\"", "ER_KILL_DENIED_ERROR": "\"Utente non proprietario del thread %lld\"", "ER_NO_TABLES_USED": "\"Nessuna tabella usata\"", "ER_TOO_BIG_SET": "\"Troppe stringhe per la colonna %-.192s e la SET\"", "ER_NO_UNIQUE_LOGFILE": "\"Impossibile generare un nome del file log unico %-.200s.(1-999)\\n\"", "ER_TABLE_NOT_LOCKED_FOR_WRITE": "\"La tabella '%-.192s' e` soggetta a lock in lettura e non puo` essere aggiornata\"", "ER_TABLE_NOT_LOCKED": "\"Non e` stato impostato il lock per la tabella '%-.192s' con LOCK TABLES\"", "ER_WRONG_DB_NAME 42000": "\"Nome database errato '%-.100T'\"", "ER_WRONG_TABLE_NAME 42000": "\"Nome tabella errato '%-.100s'\"", "ER_TOO_BIG_SELECT 42000": "\"La SELECT dovrebbe esaminare troppi record e usare troppo tempo. Controllare la WHERE e usa SET SQL_BIG_SELECTS=1 se e` tutto a posto\"", "ER_UNKNOWN_ERROR": "\"Errore sconosciuto\"", "ER_UNKNOWN_PROCEDURE 42000": "\"Procedura '%-.192s' sconosciuta\"", "ER_WRONG_PARAMCOUNT_TO_PROCEDURE 42000": "\"Numero di parametri errato per la procedura '%-.192s'\"", "ER_WRONG_PARAMETERS_TO_PROCEDURE": "\"Parametri errati per la procedura '%-.192s'\"", "ER_UNKNOWN_TABLE 42S02": "\"Tabella '%-.192s' sconosciuta in %-.32s\"", "ER_FIELD_SPECIFIED_TWICE 42000": "\"Campo '%-.192s' specificato 2 volte\"", "ER_INVALID_GROUP_FUNC_USE": "\"Uso non valido di una funzione di raggruppamento\"", "ER_UNSUPPORTED_EXTENSION 42000": "\"La tabella '%-.192s' usa un'estensione che non esiste in questa versione di MariaDB\"", "ER_TABLE_MUST_HAVE_COLUMNS 42000": "\"Una tabella deve avere almeno 1 colonna\"", "ER_RECORD_FILE_FULL": "\"La tabella '%-.192s' e` piena\"", "ER_UNKNOWN_CHARACTER_SET 42000": "\"Set di caratteri '%-.64s' sconosciuto\"", "ER_TOO_MANY_TABLES": "\"Troppe tabelle. MariaDB puo` usare solo %d tabelle in una join\"", "ER_TOO_MANY_FIELDS": "\"Troppi campi\"", "ER_TOO_BIG_ROWSIZE 42000": "\"Riga troppo grande. La massima grandezza di una riga, non contando i BLOB, e` %ld. Devi cambiare alcuni campi in BLOB\"", "ER_STACK_OVERRUN": "\"Thread stack overrun:  Usati: %ld di uno stack di %ld.  Usa 'mariadbd --thread_stack=#' per specificare uno stack piu` grande\"", "ER_WRONG_OUTER_JOIN 42000": "\"Trovata una dipendenza incrociata nella OUTER JOIN. Controlla le condizioni ON\"", "ER_CANT_FIND_UDF": "\"Impossibile caricare la funzione '%-.192s'\"", "ER_CANT_INITIALIZE_UDF": "\"Impossibile inizializzare la funzione '%-.192s'; %-.80s\"", "ER_UDF_NO_PATHS": "\"Non sono ammessi path per le librerie condivisa\"", "ER_UDF_EXISTS": "\"La funzione '%-.192s' esiste gia`\"", "ER_CANT_OPEN_LIBRARY": "\"Impossibile aprire la libreria condivisa '%-.192s' (errno: %d, %-.128s)\"", "ER_CANT_FIND_DL_ENTRY": "\"Impossibile trovare la funzione '%-.128s' nella libreria\"", "ER_FUNCTION_NOT_DEFINED": "\"La funzione '%-.192s' non e` definita\"", "ER_HOST_IS_BLOCKED": "\"Sistema '%-.64s' bloccato a causa di troppi errori di connessione. Per sbloccarlo: 'mariadb-admin flush-hosts'\"", "ER_HOST_NOT_PRIVILEGED": "\"Al sistema '%-.64s' non e` consentita la connessione a questo server MariaDB\"", "ER_PASSWORD_ANONYMOUS_USER 42000": "\"Impossibile cambiare la password usando MariaDB come utente anonimo\"", "ER_PASSWORD_NOT_ALLOWED 42000": "\"E` necessario il privilegio di update sulle tabelle del database mysql per cambiare le password per gli altri utenti\"", "ER_PASSWORD_NO_MATCH 28000": "\"Impossibile trovare la riga corrispondente nella tabella user\"", "ER_UPDATE_INFO": "\"Rows riconosciute: %ld  Cambiate: %ld  Warnings: %ld\"", "ER_CANT_CREATE_THREAD": "\"Impossibile creare un nuovo thread (errno %M). Se non ci sono problemi di memoria disponibile puoi consultare il manuale per controllare possibili problemi dipendenti dal SO\"", "ER_WRONG_VALUE_COUNT_ON_ROW 21S01": "\"Il numero delle colonne non corrisponde al conteggio alla riga %lu\"", "ER_CANT_REOPEN_TABLE": "\"Impossibile riaprire la tabella: '%-.192s'\"", "ER_INVALID_USE_OF_NULL 22004": "\"Uso scorretto del valore NULL\"", "ER_REGEXP_ERROR 42000": "\"Errore '%s' da regexp\"", "ER_MIX_OF_GROUP_FUNC_AND_FIELDS 42000": "\"Il mescolare funzioni di aggregazione (MIN(),MAX(),COUNT()...) e non e` illegale se non c'e` una clausula GROUP BY\"", "ER_NONEXISTING_GRANT 42000": "\"GRANT non definita per l'utente '%-.48s' dalla macchina '%-.64s'\"", "ER_TABLEACCESS_DENIED_ERROR 42000": "\"Comando %-.100T negato per l'utente: '%s'@'%s' sulla tabella '%-.192s'\"", "ER_COLUMNACCESS_DENIED_ERROR 42000": "\"Comando %-.32s negato per l'utente: '%s'@'%s' sulla colonna '%-.192s' della tabella '%-.192s'\"", "ER_ILLEGAL_GRANT_FOR_TABLE 42000": "\"Comando GRANT/REVOKE illegale. Prego consultare il manuale per sapere quali privilegi possono essere usati\"", "ER_GRANT_WRONG_HOST_OR_USER 42000": "\"L'argomento host o utente per la GRANT e` troppo lungo\"", "ER_NO_SUCH_TABLE 42S02": "\"La tabella '%-.192s.%-.192s' non esiste\"", "ER_NONEXISTING_TABLE_GRANT 42000": "\"GRANT non definita per l'utente '%-.48s' dalla macchina '%-.64s' sulla tabella '%-.192s'\"", "ER_NOT_ALLOWED_COMMAND 42000": "\"Il comando utilizzato non e` supportato in questa versione di MariaDB\"", "ER_SYNTAX_ERROR 42000": "\"Errore di sintassi nella query SQL\"", "ER_DELAYED_CANT_CHANGE_LOCK": "\"Il thread di inserimento ritardato non riesce ad ottenere il lock per la tabella %-.192s\"", "ER_TOO_MANY_DELAYED_THREADS": "\"Troppi threads ritardati in uso\"", "ER_ABORTING_CONNECTION 08S01": "\"Interrotta la connessione %ld al db: '%-.192s' utente: '%-.48s' (%-.64s)\"", "ER_NET_PACKET_TOO_LARGE 08S01": "\"Ricevuto un pacchetto piu` grande di 'max_allowed_packet'\"", "ER_NET_READ_ERROR_FROM_PIPE 08S01": "\"Rilevato un errore di lettura dalla pipe di connessione\"", "ER_NET_FCNTL_ERROR 08S01": "\"Rilevato un errore da fcntl()\"", "ER_NET_PACKETS_OUT_OF_ORDER 08S01": "\"Ricevuti pacchetti non in ordine\"", "ER_NET_UNCOMPRESS_ERROR 08S01": "\"Impossibile scompattare i pacchetti di comunicazione\"", "ER_NET_READ_ERROR 08S01": "\"Rilevato un errore ricevendo i pacchetti di comunicazione\"", "ER_NET_READ_INTERRUPTED 08S01": "\"Rilevato un timeout ricevendo i pacchetti di comunicazione\"", "ER_NET_ERROR_ON_WRITE 08S01": "\"Rilevato un errore inviando i pacchetti di comunicazione\"", "ER_NET_WRITE_INTERRUPTED 08S01": "\"Rilevato un timeout inviando i pacchetti di comunicazione\"", "ER_TOO_LONG_STRING 42000": "\"La stringa di risposta e` piu` lunga di 'max_allowed_packet'\"", "ER_TABLE_CANT_HANDLE_BLOB 42000": "\"Il tipo di tabella usata (%s) non supporta colonne di tipo BLOB/TEXT\"", "ER_TABLE_CANT_HANDLE_AUTO_INCREMENT 42000": "\"Il tipo di tabella usata (%s) non supporta colonne di tipo AUTO_INCREMENT\"", "ER_DELAYED_INSERT_TABLE_LOCKED": "\"L'inserimento ritardato (INSERT DELAYED) non puo` essere usato con la tabella '%-.192s', perche` soggetta a lock da 'LOCK TABLES'\"", "ER_WRONG_COLUMN_NAME 42000": "\"Nome colonna '%-.100s' non corretto\"", "ER_WRONG_MRG_TABLE": "\"Non tutte le tabelle nella tabella di MERGE sono definite in maniera identica\"", "ER_DUP_UNIQUE 23000": "\"Impossibile scrivere nella tabella '%-.192s' per limitazione di unicita`\"", "ER_BLOB_KEY_WITHOUT_LENGTH 42000": "\"La colonna '%-.192s' di tipo BLOB e` usata in una chiave senza specificarne la lunghezza\"", "ER_PRIMARY_CANT_HAVE_NULL 42000": "\"Tutte le parti di una chiave primaria devono essere dichiarate NOT NULL; se necessitano valori NULL nelle chiavi utilizzare UNIQUE\"", "ER_TOO_MANY_ROWS 42000": "\"Il risultato consiste di piu` di una riga\"", "ER_REQUIRES_PRIMARY_KEY 42000": "\"Questo tipo di tabella richiede una chiave primaria\"", "ER_NO_RAID_COMPILED": "\"Questa versione di MariaDB non e` compilata con il supporto RAID\"", "ER_UPDATE_WITHOUT_KEY_IN_SAFE_MODE": "\"In modalita` 'safe update' si e` cercato di aggiornare una tabella senza clausola WHERE su una chiave\"", "ER_KEY_DOES_NOT_EXISTS 42000 S1009": "\"La chiave '%-.192s' non esiste nella tabella '%-.192s'\"", "ER_CHECK_NO_SUCH_TABLE 42000": "\"Impossibile aprire la tabella\"", "ER_CHECK_NOT_IMPLEMENTED 42000": "\"Il gestore per la tabella non supporta il %s\"", "ER_CANT_DO_THIS_DURING_AN_TRANSACTION 25000": "\"Non puoi eseguire questo comando in una transazione\"", "ER_ERROR_DURING_COMMIT": "\"Rilevato l'errore %M durante il COMMIT\"", "ER_ERROR_DURING_ROLLBACK": "\"Rilevato l'errore %M durante il ROLLBACK\"", "ER_ERROR_DURING_FLUSH_LOGS": "\"Rilevato l'errore %M durante il FLUSH_LOGS\"", "ER_ERROR_DURING_CHECKPOINT": "\"Rilevato l'errore %M durante il CHECKPOINT\"", "ER_NEW_ABORTING_CONNECTION 08S01": "\"Interrotta la connessione %lld al db: ''%-.192s' utente: '%-.48s' host: '%-.64s' (%-.64s)\"", "ER_INDEX_REBUILD": "\"Fallita la ricostruzione dell'indice della tabella copiata '%-.192s'\"", "ER_MASTER": "\"Errore dal master: '%-.64s\"", "ER_MASTER_NET_READ 08S01": "\"Errore di rete durante la ricezione dal master\"", "ER_MASTER_NET_WRITE 08S01": "\"Errore di rete durante l'invio al master\"", "ER_FT_MATCHING_KEY_NOT_FOUND": "\"Impossibile trovare un indice FULLTEXT che corrisponda all'elenco delle colonne\"", "ER_LOCK_OR_ACTIVE_TRANSACTION": "\"Impossibile eseguire il comando richiesto: tabelle sotto lock o transazione in atto\"", "ER_UNKNOWN_SYSTEM_VARIABLE": "\"Variabile di sistema '%-.*s' sconosciuta\"", "ER_CRASHED_ON_USAGE": "\"La tabella '%-.192s' e` segnalata come corrotta e deve essere riparata\"", "ER_CRASHED_ON_REPAIR": "\"La tabella '%-.192s' e` segnalata come corrotta e l'ultima ricostruzione (automatica?) e` fallita\"", "ER_WARNING_NOT_COMPLETE_ROLLBACK": "\"Attenzione: Alcune delle modifiche alle tabelle non transazionali non possono essere ripristinate (roll back impossibile)\"", "ER_TRANS_CACHE_FULL": "\"La transazione a comandi multipli (multi-statement) ha richiesto piu` di 'max_binlog_cache_size' bytes di disco: aumentare questa variabile di mariadbd e riprovare\"", "ER_SLAVE_MUST_STOP": "\"Questa operazione non puo' essere eseguita con un database 'slave' '%2$*1$s' che gira, lanciare prima STOP SLAVE '%2$*1$s'\"", "ER_SLAVE_NOT_RUNNING": "\"Questa operaione richiede un database 'slave', configurarlo ed eseguire START SLAVE\"", "ER_BAD_SLAVE": "\"Il server non e' configurato come 'slave', correggere il file di configurazione cambiando CHANGE MASTER TO\"", "ER_SLAVE_THREAD": "\"Impossibile creare il thread 'slave', controllare le risorse di sistema\"", "ER_TOO_MANY_USER_CONNECTIONS 42000": "\"L'utente %-.64s ha gia' piu' di 'max_user_connections' connessioni attive\"", "ER_SET_CONSTANTS_ONLY": "\"Si possono usare solo espressioni costanti con SET\"", "ER_LOCK_WAIT_TIMEOUT": "\"E' scaduto il timeout per l'attesa del lock\"", "ER_LOCK_TABLE_FULL": "\"Il numero totale di lock e' maggiore della grandezza della tabella di lock\"", "ER_READ_ONLY_TRANSACTION 25000": "\"I lock di aggiornamento non possono essere acquisiti durante una transazione 'READ UNCOMMITTED'\"", "ER_DROP_DB_WITH_READ_LOCK": "\"DROP DATABASE non e' permesso mentre il thread ha un lock globale di lettura\"", "ER_CREATE_DB_WITH_READ_LOCK": "\"CREATE DATABASE non e' permesso mentre il thread ha un lock globale di lettura\"", "ER_WRONG_ARGUMENTS": "\"Argomenti errati a %s\"", "ER_NO_PERMISSION_TO_CREATE_USER 42000": "\"A '%s'@'%s' non e' permesso creare nuovi utenti\"", "ER_UNION_TABLES_IN_DIFFERENT_DIR": "\"Definizione della tabella errata; tutte le tabelle di tipo MERGE devono essere nello stesso database\"", "ER_LOCK_DEADLOCK 40001": "\"Trovato deadlock durante il lock; Provare a far ripartire la transazione\"", "ER_TABLE_CANT_HANDLE_FT": "\"La tabella usata (%s) non supporta gli indici FULLTEXT\"", "ER_CANNOT_ADD_FOREIGN": "\"Impossibile aggiungere il vincolo di integrita' referenziale (foreign key constraint) a `%s`\"", "ER_NO_REFERENCED_ROW 23000": "\"Impossibile aggiungere la riga: un vincolo d'integrita' referenziale non e' soddisfatto\"", "ER_ROW_IS_REFERENCED 23000": "\"Impossibile cancellare la riga: un vincolo d'integrita' referenziale non e' soddisfatto\"", "ER_CONNECT_TO_MASTER 08S01": "\"Errore durante la connessione al master: %-.128s\"", "ER_QUERY_ON_MASTER": "\"Errore eseguendo una query sul master: %-.128s\"", "ER_ERROR_WHEN_EXECUTING_COMMAND": "\"Errore durante l'esecuzione del comando %s: %-.128s\"", "ER_WRONG_USAGE": "\"Uso errato di %s e %s\"", "ER_WRONG_NUMBER_OF_COLUMNS_IN_SELECT 21000": "\"La SELECT utilizzata ha un numero di colonne differente\"", "ER_CANT_UPDATE_WITH_READLOCK": "\"Impossibile eseguire la query perche' c'e' un conflitto con in lock di lettura\"", "ER_MIXING_NOT_ALLOWED": "\"E' disabilitata la possibilita' di mischiare tabelle transazionali e non-transazionali\"", "ER_DUP_ARGUMENT": "\"L'opzione '%s' e' stata usata due volte nel comando\"", "ER_USER_LIMIT_REACHED 42000": "\"L'utente '%-.64s' ha ecceduto la risorsa '%s' (valore corrente: %ld)\"", "ER_SPECIFIC_ACCESS_DENIED_ERROR 42000": "\"Accesso non consentito. Serve il privilegio %-.128s per questa operazione\"", "ER_LOCAL_VARIABLE": "\"La variabile '%-.64s' e' una variabile locale ( SESSION ) e non puo' essere cambiata usando SET GLOBAL\"", "ER_GLOBAL_VARIABLE": "\"La variabile '%-.64s' e' una variabile globale ( GLOBAL ) e deve essere cambiata usando SET GLOBAL\"", "ER_NO_DEFAULT 42000": "\"La variabile '%-.64s' non ha un valore di default\"", "ER_WRONG_VALUE_FOR_VAR 42000": "\"Alla variabile '%-.64s' non puo' essere assegato il valore '%-.200T'\"", "ER_WRONG_TYPE_FOR_VAR 42000": "\"Tipo di valore errato per la variabile '%-.64s'\"", "ER_VAR_CANT_BE_READ": "\"Alla variabile '%-.64s' e' di sola scrittura quindi puo' essere solo assegnato un valore, non letto\"", "ER_CANT_USE_OPTION_HERE 42000": "\"Uso/posizione di '%s' sbagliato\"", "ER_NOT_SUPPORTED_YET 42000": "\"Questa versione di MariaDB non supporta ancora '%s'\"", "ER_MASTER_FATAL_ERROR_READING_BINLOG": "\"Errore fatale %d: '%-.320s' dal master leggendo i dati dal log binario\"", "ER_DUP_ENTRY_WITH_KEY_NAME 23000 S1009": "\"Valore duplicato '%-.64T' per la chiave '%-.192s'\"", "ER_ACCESS_DENIED_NO_PASSWORD_ERROR 28000": "\"Accesso non consentito per l'utente: '%s'@'%s'\"", "ER_DUP_UNKNOWN_IN_INDEX 23000": "\"Valore duplicato per la chiave '%-.192s'\""}